CHANGELOG
LICENSE
MANIFEST.in
NOTICE
README.md
setup.py
test.py
lz4/LICENSE
lz4/NEWS
lz4/lz4.c
lz4/lz4.h
lz4/lz4frame.c
lz4/lz4frame.h
lz4/lz4frame_static.h
lz4/lz4hc.c
lz4/lz4hc.h
lz4/lz4opt.h
lz4/xxhash.c
lz4/xxhash.h
lz4framed/__init__.py
lz4framed/__main__.py
lz4framed/compat.py
lz4framed/py-lz4framed.c
py_lz4framed_ph4.egg-info/PKG-INFO
py_lz4framed_ph4.egg-info/SOURCES.txt
py_lz4framed_ph4.egg-info/dependency_links.txt
py_lz4framed_ph4.egg-info/not-zip-safe
py_lz4framed_ph4.egg-info/top_level.txt