Metadata-Version: 1.1
Name: py-lz4framed-ph4
Version: 0.9.11
Summary: LZ4Frame library for Python (via C bindings)
Home-page: https://github.com/ph4r05/py-lz4framed
Author: Dusan Klinec (ph4r05)
Author-email: dusan.klinec@gmail.com
License: Apache License 2.0
Keywords: lz4framed,lz4frame,lz4
Platform: UNKNOWN
Classifier: Development Status :: 5 - Production/Stable
Classifier: License :: OSI Approved :: Apache Software License
Classifier: Intended Audience :: Developers
Classifier: Programming Language :: C
Classifier: Programming Language :: Python
Classifier: Programming Language :: Python :: 2.7
Classifier: Programming Language :: Python :: 3.2
Classifier: Programming Language :: Python :: 3.3
Classifier: Programming Language :: Python :: 3.4
Classifier: Programming Language :: Python :: 3.5
Classifier: Programming Language :: Python :: 3.6
Classifier: Topic :: Software Development :: Libraries
Classifier: Topic :: Software Development :: Libraries :: Python Modules
